simple_categorisation/__init__.py
simple_categorisation/sankey.py
simple_categorisation/simple.py
simple_categorisation-0.2.dist-info/METADATA
simple_categorisation-0.2.dist-info/WHEEL
simple_categorisation-0.2.dist-info/top_level.txt
simple_categorisation-0.2.dist-info/RECORD
